skwdro/__init__.py
skwdro/_template.py
skwdro/_version.py
skwdro/torch.py
skwdro/wrap_problem.py
skwdro/base/cost_decoder.py
skwdro/base/problems.py
skwdro/base/rho_tuners.py
skwdro/base/rho_tuners_computations.py
skwdro/base/costs_torch/__init__.py
skwdro/base/costs_torch/base_cost.py
skwdro/base/costs_torch/normcost.py
skwdro/base/costs_torch/normlabelcost.py
skwdro/base/losses_torch/__init__.py
skwdro/base/losses_torch/base_loss.py
skwdro/base/losses_torch/logistic.py
skwdro/base/losses_torch/newsvendor.py
skwdro/base/losses_torch/portfolio.py
skwdro/base/losses_torch/quadratic.py
skwdro/base/losses_torch/weber.py
skwdro/base/losses_torch/wrapper.py
skwdro/base/samplers/torch/__init__.py
skwdro/base/samplers/torch/base_samplers.py
skwdro/base/samplers/torch/classif_sampler.py
skwdro/base/samplers/torch/cost_samplers.py
skwdro/base/samplers/torch/newsvendor_sampler.py
skwdro/base/samplers/torch/portfolio_sampler.py
skwdro/distributions/__init__.py
skwdro/distributions/dirac_distribution.py
skwdro/linear_models/__init__.py
skwdro/linear_models/_linear_regression.py
skwdro/linear_models/_logistic_regression.py
skwdro/neural_network/__init__.py
skwdro/neural_network/_loss_shallownet.py
skwdro/neural_network/_shallow_net.py
skwdro/operations_research/__init__.py
skwdro/operations_research/_newsvendor.py
skwdro/operations_research/_portfolio.py
skwdro/operations_research/_weber.py
skwdro/solvers/__init__.py
skwdro/solvers/entropic_dual_torch.py
skwdro/solvers/entropic_dual_torch_epsilon.py
skwdro/solvers/hybrid_opt.py
skwdro/solvers/optim_cond.py
skwdro/solvers/oracle_torch.py
skwdro/solvers/result.py
skwdro/solvers/specific_solvers.py
skwdro/solvers/utils.py
skwdro/solvers/_dual_interfaces/__init__.py
skwdro/solvers/_dual_interfaces/_impsamp_interface.py
skwdro/solvers/_dual_interfaces/_misc_dual_interfaces.py
skwdro/solvers/_dual_interfaces/dual_loss.py
skwdro/tests/__init__.py
skwdro/tests/test_common.py
skwdro-1.1.1.dist-info/METADATA
skwdro-1.1.1.dist-info/WHEEL
skwdro-1.1.1.dist-info/licenses/LICENSE
skwdro-1.1.1.dist-info/RECORD
