Metadata-Version: 2.3
Name: skwdro
Version: 1.1.1
Summary: A Robust ML toolbox
Project-URL: Download, https://github.com/iutzeler/skwdro
Maintainer-email: "F. Iutzeler" <franck.iutzeler@gmail.com>
Classifier: Intended Audience :: Developers
Classifier: Intended Audience :: Science/Research
Classifier: License :: OSI Approved
Classifier: Operating System :: MacOS
Classifier: Operating System :: Microsoft :: Windows
Classifier: Operating System :: POSIX
Classifier: Operating System :: Unix
Classifier: Programming Language :: Python
Classifier: Programming Language :: Python :: 2.7
Classifier: Programming Language :: Python :: 3.5
Classifier: Programming Language :: Python :: 3.6
Classifier: Programming Language :: Python :: 3.7
Classifier: Topic :: Scientific/Engineering
Classifier: Topic :: Software Development
Requires-Dist: cvxopt
Requires-Dist: cvxpy
Requires-Dist: dask[distributed]
Requires-Dist: mechanic-pytorch
Requires-Dist: numpy
Requires-Dist: pandas
Requires-Dist: prodigyopt
Requires-Dist: scikit-learn>=1.4
Requires-Dist: scipy
Requires-Dist: sqwash
Requires-Dist: torch
Provides-Extra: docs
Requires-Dist: furo; extra == 'docs'
Requires-Dist: myst-parser; extra == 'docs'
Requires-Dist: numpydoc; extra == 'docs'
Requires-Dist: sphinx; extra == 'docs'
Requires-Dist: sphinx-copybutton; extra == 'docs'
Requires-Dist: sphinx-design; extra == 'docs'
Requires-Dist: sphinx-gallery; extra == 'docs'
Requires-Dist: sphinx-rtd-theme; extra == 'docs'
Provides-Extra: examples
Requires-Dist: joblib; extra == 'examples'
Requires-Dist: matplotlib; extra == 'examples'
Requires-Dist: seaborn; extra == 'examples'
Requires-Dist: torchvision; extra == 'examples'
Requires-Dist: tqdm; extra == 'examples'
Provides-Extra: monitor
Requires-Dist: wandb; extra == 'monitor'
Provides-Extra: test
Requires-Dist: mypy>=1.13; extra == 'test'
Requires-Dist: pycodestyle; extra == 'test'
Requires-Dist: pytest; extra == 'test'
Requires-Dist: pytest-cov; extra == 'test'
Requires-Dist: pytest-rerunfailures; extra == 'test'
Requires-Dist: ruff; extra == 'test'
